latis/__init__.py
latis/ImageProcessing/GenericOp.py
latis/ImageProcessing/Image.py
latis/ImageProcessing/ImageIO.py
latis/ImageProcessing/OprationManager.py
latis/ImageProcessing/__init__.py
latis_image_proccessing-0.0.19.dist-info/METADATA
latis_image_proccessing-0.0.19.dist-info/WHEEL
latis_image_proccessing-0.0.19.dist-info/top_level.txt
latis_image_proccessing-0.0.19.dist-info/RECORD
