Metadata-Version: 2.1
Name: latis-image-proccessing
Version: 0.0.19
Summary: LATIS image processing utilities for python
Home-page: http://www.latis-eniso.org/
Author: Mohamed Amine
Author-email: hiddentn@outlook.com
License: UNKNOWN
Platform: UNKNOWN
Classifier: Programming Language :: Python :: 3.0
Classifier: License :: OSI Approved :: MIT License
Requires-Python: >=3.0
Requires-Dist: pydicom
Requires-Dist: numpy
Requires-Dist: Pillow
